README.md
setup.cfg
setup.py
plasticity/__init__.py
plasticity/version.py
plasticity.egg-info/PKG-INFO
plasticity.egg-info/SOURCES.txt
plasticity.egg-info/dependency_links.txt
plasticity.egg-info/requires.txt
plasticity.egg-info/top_level.txt
plasticity/base/__init__.py
plasticity/base/endpoint.py
plasticity/base/service.py
plasticity/cortex/__init__.py
plasticity/sapien/__init__.py
plasticity/sapien/core.py
plasticity/sapien/names.py
plasticity/sapien/transform.py
plasticity/utils/__init__.py
plasticity/utils/utils.py
test/__init__.py
test/test_utils.py